sier2_blocks_datamap/blocks/__init__.py
sier2_blocks_datamap/blocks/thisnotthat.py
sier2_blocks_datamap/blocks/umap.py
sier2_blocks_datamap/dags/__init__.py
sier2_blocks_datamap/dags/datamap.py
sier2_blocks_datamap/shelf/__init__.py
sier2_blocks_datamap-0.4.dist-info/LICENSE
sier2_blocks_datamap-0.4.dist-info/METADATA
sier2_blocks_datamap-0.4.dist-info/WHEEL
sier2_blocks_datamap-0.4.dist-info/entry_points.txt
sier2_blocks_datamap-0.4.dist-info/RECORD
