Metadata-Version: 2.3
Name: sier2-blocks-datamap
Version: 0.4
Summary: Datamap blocks for sier2
Author: jacobgolding
Author-email: jacobgolding <jacobgolding@users.noreply.github.com>
Classifier: Programming Language :: Python :: 3.11
Classifier: Operating System :: OS Independent
Classifier: Intended Audience :: Science/Research
Classifier: Intended Audience :: Developers
Classifier: Topic :: Scientific/Engineering
Classifier: Topic :: Software Development :: Libraries
